dog/__init__.py
random_dog-1.0.2.dist-info/LICENSE
random_dog-1.0.2.dist-info/METADATA
random_dog-1.0.2.dist-info/WHEEL
random_dog-1.0.2.dist-info/entry_points.txt
random_dog-1.0.2.dist-info/top_level.txt
random_dog-1.0.2.dist-info/RECORD
